damv1xproductionk8salertreleasev2/__init__.py
damv1xproductionk8salertreleasev2/myproductionk8salert_release_v2.py
damv1xproductionk8salertreleasev2-0.0.9.dist-info/METADATA
damv1xproductionk8salertreleasev2-0.0.9.dist-info/WHEEL
damv1xproductionk8salertreleasev2-0.0.9.dist-info/top_level.txt
damv1xproductionk8salertreleasev2-0.0.9.dist-info/RECORD
