Metadata-Version: 2.1
Name: damv1xproductionk8salertreleasev2
Version: 0.0.9
Summary: productionk8salertreleasev2 package
Home-page: UNKNOWN
Author: dhonyabumuhammad (Bekasi)
Author-email: <dhony.priniardi.m@gmail.com>
License: UNKNOWN
Keywords: k8salertrelease
Platform: UNKNOWN
Classifier: Development Status :: 1 - Planning
Classifier: Intended Audience :: Developers
Classifier: Programming Language :: Python :: 3
Classifier: Operating System :: Unix
Classifier: Operating System :: MacOS :: MacOS X
Classifier: Operating System :: Microsoft :: Windows
Requires-Dist: damv1env
Requires-Dist: damv1time7
Requires-Dist: damv1kubectl
Requires-Dist: damv1manipulation
Requires-Dist: damv1templateprojectk8salert
Requires-Dist: damv1evernoteprojectk8salert
Requires-Dist: damv1telegramprojectk8salert
Requires-Dist: damv1airtableprojectk8salert
